Metadata-Version: 2.1
Name: erddap-catalog-chunk-editor
Version: 1.0.0
Summary: Common python library for CEOTR data team
Home-page: https://gitlab.oceantrack.org/ceotr-public/ceotr_app_common/errdap-catalog-chunk-editor
Author: CEOTR
Author-email: support@ceotr.ca
License: GNU General Public License v3 (GPLv3)
License-File: LICENSE.md
